{
   "abstract" : "Lightweight HTTP server",
   "author" : [
      "Best Practical Solutions, LLC <modules@bestpractical.com>"
   ],
   "dynamic_config" : 0,
   "generated_by" : "Module::Install version 1.17, CPAN::Meta::Converter version 2.150010",
   "license" : [
      "perl_5"
   ],
   "meta-spec" : {
      "url" : "http://search.cpan.org/perldoc?CPAN::Meta::Spec",
      "version" : 2
   },
   "name" : "HTTP-Server-Simple",
   "no_index" : {
      "directory" : [
         "inc",
         "t"
      ]
   },
   "prereqs" : {
      "build" : {
         "requires" : {
            "ExtUtils::MakeMaker" : "6.36"
         }
      },
      "configure" : {
         "requires" : {
            "ExtUtils::MakeMaker" : "0"
         }
      },
      "runtime" : {
         "requires" : {
            "CGI" : "0",
            "Socket" : "1.94",
            "Test::More" : "0"
         }
      }
   },
   "release_status" : "stable",
   "resources" : {
      "license" : [
         "http://dev.perl.org/licenses/"
      ],
      "repository" : {
         "url" : "https://github.com/bestpractical/http-server-simple"
      }
   },
   "version" : "0.52",
   "x_module_name" : "HTTP::Server::Simple",
   "x_serialization_backend" : "JSON::PP version 4.04"
}
